{"stem":"28.3","instances":[{"docId":"D_000144-002-000","docUri":"D_000144-002-000.html","score":1,"contexts":[{"form":"28.3","weight":"1","pos":7,"context":"...S. Fischer Verlags A.G. hat mir Ihren Brief vom <mark>28.3<\/mark>. mit dem Ersuchen der weiteren Bear beitung der...","fid":"p__37"}]},{"docId":"D_000100-003-000","docUri":"D_000100-003-000.html","score":1,"contexts":[{"form":"28.3","weight":"1","pos":42,"context":"...3Betr. Kraus – Schober exp. am <mark>28.3<\/mark>.1928.","fid":"note__5"}]}]}