{"stem":"beitern","instances":[{"docId":"D_000039-003-000","docUri":"D_000039-003-000.html","score":1,"contexts":[{"form":"beitern","weight":"1","pos":90,"context":"...abgelehnt und seine Bereitschaft, vor den Wiener Ar <mark>beitern<\/mark> zu lesen, von der Erfüllung der Bedingung abhän...","fid":"note__36"}]},{"docId":"D_000026-001-000","docUri":"D_000026-001-000.html","score":1,"contexts":[{"form":"beitern","weight":"1","pos":167,"context":"...sein Drang, Kunststelle und Parteiführer bei den Ar <mark>beitern<\/mark> selbst zu verpetzen, ––“ (§ 491 St.G....","fid":"p__22"}]}]}