{"stem":"betitelten","instances":[{"docId":"D_000195-020-000","docUri":"D_000195-020-000.html","score":1,"contexts":[{"form":"betitelten","weight":"1","pos":62,"context":"...23 dieser Zeitschrift einen „Die Fackel schwelt“ <mark>betitelten<\/mark> mit dem Pseudonym LucienVerneau gezeichneten Artikel veröffentlicht haben, in...","fid":"p__41"}]},{"docId":"D_000019-002-000","docUri":"D_000019-002-000.html","score":1,"contexts":[{"form":"betitelten","weight":"1","pos":49,"context":"...einem von ihm unter zeichneten mit „Preisausschreiben“ <mark>betitelten<\/mark> Artikel mich durch die Bezeichnung „Vortragsaffe“ beschimpft....","fid":"p__38"}]}]}