{"stem":"eingefallen","instances":[{"docId":"D_000134-047-000","docUri":"D_000134-047-000.html","score":2,"contexts":[{"form":"eingefallen","weight":"1","pos":1131,"context":"...allen Punkten übereinstimmt, so wäre es ihm nicht <mark>eingefallen<\/mark>, sich der Beweisführung über einen Sachverhalt auszusetzen,...","fid":"p__83"},{"form":"eingefallen","weight":"1","pos":3702,"context":"...allen Punkten übereinstimmt, so wäre es ihm nicht <mark>eingefallen<\/mark>, sich der Beweisführung über einen Sach verhalt auszusetzen...","fid":"p__80"}]},{"docId":"D_000076-012-000","docUri":"D_000076-012-000.html","score":1,"contexts":[{"form":"eingefallen","weight":"1","pos":90,"context":"..., das uns Ihnen gegen über seit Jahren nicht <mark>eingefallen<\/mark> ist. Aber auch die Ankündigung einer der Publikation würde,...","fid":"p__61"}]},{"docId":"D_000196-109-000","docUri":"D_000196-109-000.html","score":1,"contexts":[{"form":"eingefallen","weight":"1","pos":6,"context":" Leider etwas zu spät ist mir <mark>eingefallen<\/mark>, dass es doch zweckmässiger wäre, mehrere Geschwister des...","fid":"p__19"}]},{"docId":"D_000195-048-000","docUri":"D_000195-048-000.html","score":1,"contexts":[{"form":"eingefallen","weight":"1","pos":6,"context":" Leider etwas zu spät ist mir <mark>eingefallen<\/mark>, dass es doch zweckmässiger wäre, mehrere Geschwister des...","fid":"p__19"}]},{"docId":"D_000144-034-000","docUri":"D_000144-034-000.html","score":1,"contexts":[{"form":"eingefallen","weight":"1","pos":51,"context":"...solche Auswahl herauszugeben, ist uns erst jetzt nachträglich <mark>eingefallen<\/mark>. Wir zweifeln ja nicht daran, dass eine solche...","fid":"p__23"}]},{"docId":"D_000125-076-000","docUri":"D_000125-076-000.html","score":1,"contexts":[{"form":"eingefallen","weight":"1","pos":45,"context":"...mit eigenen Kräften aufzuführen. Es ist mir nun <mark>eingefallen<\/mark>, ob es nun nicht möglich wäre, schon in...","fid":"p__25"}]},{"docId":"D_000193-095-000","docUri":"D_000193-095-000.html","score":1,"contexts":[{"form":"eingefallen","weight":"1","pos":16,"context":"...wurde. Es sind mir nach träglich noch einige Argumente <mark>eingefallen<\/mark>, die Sie vielleicht bei der Berufung verwenden können....","fid":"p__37"}]},{"docId":"D_000193-088-000","docUri":"D_000193-088-000.html","score":1,"contexts":[{"form":"eingefallen","weight":"1","pos":51,"context":"...möchte nur noch bekanntgeben, was mir weiters dazu <mark>eingefallen<\/mark> ist. Wenn der Richter auf dem Standpunkte steht, dass...","fid":"p__84"}]},{"docId":"D_000134-032-000","docUri":"D_000134-032-000.html","score":1,"contexts":[{"form":"eingefallen","weight":"1","pos":1511,"context":"...Komposition ableugnen wolle. Dies ist mir jedoch nie <mark>eingefallen<\/mark>. Ich habe nur den vom Herrn Angeklagten in...","fid":"p__85"}]},{"docId":"D_000193-099-000","docUri":"D_000193-099-000.html","score":1,"contexts":[{"form":"eingefallen","weight":"1","pos":283,"context":"...sind Herrn K. und auch mir einige verwendbare Argumente <mark>eingefallen<\/mark>, die ich Ihnen mitteile, wobei die Auswahl...","fid":"p__19"}]},{"docId":"D_000076-007-000","docUri":"D_000076-007-000.html","score":1,"contexts":[{"form":"eingefallen","weight":"1","pos":498,"context":"...privaten Dank verdienen. Es wäre ihm selbstverständlich niemals <mark>eingefallen<\/mark> auf eine Sendung von Shakespeare-Übersetzungen mit einem...","fid":"p__93"}]},{"docId":"D_000176-019-000","docUri":"D_000176-019-000.html","score":1,"contexts":[{"form":"eingefallen","weight":"1","pos":23,"context":"...auf Aufführung des Werkes, ist mir nach träglich <mark>eingefallen<\/mark>, dass auch zu prüfen wäre, ob Herr Kraus...","fid":"p__26"}]}]}