{"stem":"einheit","instances":[{"docId":"D_000196-084-000","docUri":"D_000196-084-000.html","score":2,"contexts":[{"form":"Einheit","weight":"1","pos":1093,"context":"...müssen wie aussen und die anzuschauen das Gefühl dieser <mark>Einheit<\/mark> bestätigt und hundertmal das Gefühl, dass der Militärhass...","fid":"p__66"},{"form":"Einheit","weight":"1","pos":6571,"context":"...wie aussen und die anzu schauen das Gefühl dieser <mark>Einheit<\/mark> bestätigt und hundertmal das Gefühl, dass der Militärhass...","fid":"p__40"}]},{"docId":"D_000136-006-000","docUri":"D_000136-006-000.html","score":1,"contexts":[{"form":"Einheit","weight":"1","pos":223,"context":"...§ 9 des Vertrages – Der Vertrag stellt eine <mark>Einheit<\/mark> dar, § 8 deckt § 9 – entgegen...","fid":"p__35"}]},{"docId":"D_000027-019-000","docUri":"D_000027-019-000.html","score":1,"contexts":[{"form":"Einheits","weight":"1","pos":68,"context":"...… S 5.– Hauptleistung 15% für Nebenleistungen nach dem <mark>Einheits<\/mark> satze des § 26 Abs. 3a) und §...","fid":"p__34"}]},{"docId":"D_000070-010-000","docUri":"D_000070-010-000.html","score":1,"contexts":[{"form":"Einheit","weight":"1","pos":1063,"context":"...streitet, eine durch den Kriegszweck zusammenge haltene innere <mark>Einheit<\/mark>. Soweit der Antragsgegner einzelne dieser Gedichte zum Abdruck...","fid":"p__96"}]},{"docId":"D_000127-014-000","docUri":"D_000127-014-000.html","score":1,"contexts":[{"form":"Einheits","weight":"1","pos":69,"context":"...ent spricht nicht den gesetzlichen Vorschriften. In dem <mark>Einheits<\/mark> satz zur Berufungsverhandlung sind sämtliche Schritte die zur Information...","fid":"p__40"}]},{"docId":"D_000196-061-000","docUri":"D_000196-061-000.html","score":1,"contexts":[{"form":"Einheit","weight":"1","pos":93,"context":"...… wie aussen und die anzuschauen das Gefühl dieser <mark>Einheit<\/mark> bestätigt und hundertmal das Gefühl, dass der Militärhass...","fid":"p__21"}]},{"docId":"D_000066-014-000","docUri":"D_000066-014-000.html","score":1,"contexts":[{"form":"einheitli","weight":"1","pos":282,"context":"...nun an dieser durch die Identität der Tat gegebenen <mark>einheitli<\/mark> chen Kostenersatzpflicht nichts ändern und es wäre daher folge...","fid":"p__25"}]},{"docId":"D_000193-032-000","docUri":"D_000193-032-000.html","score":1,"contexts":[{"form":"Einheit","weight":"1","pos":204,"context":"...dem einmaligen, nie trügen den Empfinden für die <mark>Einheit<\/mark> von Wort und Begriff, für die „Wahrheit“...","fid":"p__55"}]},{"docId":"D_000066-012-000","docUri":"D_000066-012-000.html","score":1,"contexts":[{"form":"Einheits","weight":"1","pos":83,"context":" 8. April 1927 Antrag auf Kostenbestimmung samt <mark>Einheits<\/mark> satz S 5.75 Stempel S 1.— S 145.75 S...","fid":"p__22"}]},{"docId":"D_000034-021-000","docUri":"D_000034-021-000.html","score":1,"contexts":[{"form":"Einheits","weight":"1","pos":153,"context":"...des Rechtsanwalts tarifes, Bundesgesetzblatt Nr. 220, der <mark>Einheits<\/mark> satz rückwirkend mit 20. August 1926 auf 40 %...","fid":"p__28"}]},{"docId":"D_000027-016-000","docUri":"D_000027-016-000.html","score":1,"contexts":[{"form":"Einheits","weight":"1","pos":125,"context":"...Kostenbestimmung und Kostennote S 10.– anstatt S 5.– samt <mark>Einheits<\/mark> satz bestimmt wurde, endlich jedoch, dass der Richter erster...","fid":"p__70"}]}]}