{"stem":"entent","instances":[{"docId":"D_000068-074-000","docUri":"D_000068-074-000.html","score":3,"contexts":[{"form":"Entente","weight":"1","pos":2698,"context":"...dieser Tatsache (seines Wunsches nach gründlicherer Niedertretung durch die <mark>Entente<\/mark>), „Stimmung für ein Gerichtsverfahren ma 190chen“...","fid":"note__7"},{"form":"Entente","weight":"1","pos":2714,"context":"...und entkräftet nichts. Der Wunsch nach weiteren Taten der <mark>Entente<\/mark> soll sich, gibt er jetzt vor, nur auf diese...","fid":"note__13"},{"form":"Entente","weight":"1","pos":3072,"context":"...vom Urheber deutschfeindlicher Rohheiten, der noch hinterher die <mark>Entente<\/mark> zur ganzen Arbeit herbei wünscht, beschimpft werden kann,...","fid":"note__22"}]},{"docId":"D_000134-047-000","docUri":"D_000134-047-000.html","score":1,"contexts":[{"form":"Entente","weight":"1","pos":1957,"context":"...seinerzeit im Einverständnis mit Herrn Vaugoin den Blicken der <mark>Entente<\/mark> entzogen werden sollten, ","fid":"p__82"}]},{"docId":"D_000068-062-000","docUri":"D_000068-062-000.html","score":1,"contexts":[{"form":"Entente","weight":"1","pos":7061,"context":"...wen er sich be zogen und welcherlei Endsieg die <mark>Entente<\/mark> unterlassen hat; der Nach satz:","fid":"note__10"}]},{"docId":"D_000068-022-001","docUri":"D_000068-022-001.html","score":1,"contexts":[{"form":"Entente","weight":"1","pos":186,"context":" Die <mark>Entente<\/mark>, glaubt es nur, Sehnt sich nach der Heilungskur...","fid":"p__23"}]},{"docId":"D_000068-044-000","docUri":"D_000068-044-000.html","score":1,"contexts":[{"form":"Entente","weight":"1","pos":2069,"context":"...„Alles in allem geht meine Ansicht dahin, dass die <mark>Entente<\/mark> halbe Arbeit geleistet hat“ – ","fid":"p__116"}]}]}