{"stem":"gegebenenfal","instances":[{"docId":"D_000195-008-000","docUri":"D_000195-008-000.html","score":1,"contexts":[{"form":"gegebenenfalls","weight":"1","pos":168,"context":"..., deren Zusendung an Sie ich veran lasst habe, <mark>gegebenenfalls<\/mark> vorzulegen. ","fid":"p__12"}]},{"docId":"D_000019-009-000","docUri":"D_000019-009-000.html","score":1,"contexts":[{"form":"gegebenenfalls","weight":"1","pos":281,"context":"...nicht die Übertretung nach § 496St.G., sondern <mark>gegebenenfalls<\/mark> das durch die Presse begange ne Vergehen nach §...","fid":"p__102"}]},{"docId":"D_000130-040-000","docUri":"D_000130-040-000.html","score":1,"contexts":[{"form":"gegebenenfalls","weight":"1","pos":346,"context":"...möglich, da viel leicht Rückfragen erforderlich sind und ich <mark>gegebenenfalls<\/mark> mit dem Gegenanwalt noch die Fassung des Vergleichs festlegen...","fid":"p__19"}]},{"docId":"D_000023-029-000","docUri":"D_000023-029-000.html","score":1,"contexts":[{"form":"gegebenenfalls","weight":"1","pos":85,"context":"...höflichst ersucht, bekannt zu geben, ob jemand, <mark>gegebenenfalls<\/mark> wer, auf unlauterem Wege versuchte dort gerichtlich dem Emmerich...","fid":"p__25"}]},{"docId":"D_000130-031-000","docUri":"D_000130-031-000.html","score":1,"contexts":[{"form":"gegebenenfalls","weight":"1","pos":835,"context":"...selbst die gewünschte Reha bilitierung bewirken, die wir <mark>gegebenenfalls<\/mark> zu veröffentlichen nun mehr selbstverständlich bereit sind. ","fid":"p__60"}]},{"docId":"D_000115-007-000","docUri":"D_000115-007-000.html","score":1,"contexts":[{"form":"gegebenenfalls","weight":"1","pos":57,"context":"...Besitzes vorliegt. Ich nehme an, dass Sie sich <mark>gegebenenfalls<\/mark>, um Ihr Vorgehen unbedenklich er scheinen zu lassen...","fid":"p__31"}]},{"docId":"D_000193-190-000","docUri":"D_000193-190-000.html","score":1,"contexts":[{"form":"gegebenenfalls","weight":"1","pos":57,"context":"...bitte Sie nun um Ihre freundliche Zusage, mir <mark>gegebenenfalls<\/mark> die notwendigen Unterlagen in Übersetzungen einzu senden, wofür...","fid":"p__32"}]},{"docId":"D_000125-110-000","docUri":"D_000125-110-000.html","score":1,"contexts":[{"form":"gegebenenfalls","weight":"1","pos":1351,"context":"...des Unternehmens ist der Betrieb des Münchener Volkstheaters, <mark>gegebenenfalls<\/mark> auch eines anderen Theaterunternehmens irgendwelcher Art. Stammkapital:...","fid":"p__178"}]},{"docId":"D_000019-030-000","docUri":"D_000019-030-000.html","score":1,"contexts":[{"form":"gegebenenfalls","weight":"1","pos":493,"context":"...des §496 STG. anzusehen ist und weil <mark>gegebenenfalls<\/mark> durch die Form und nicht durch den Inhalt der...","fid":"p__33"}]},{"docId":"D_000130-015-000","docUri":"D_000130-015-000.html","score":1,"contexts":[{"form":"gegebenenfalls","weight":"1","pos":176,"context":"...Albrecht selbst die gewünschte Rehabilitierung bewirken, die wir <mark>gegebenenfalls<\/mark> zu veröffentlichen nunmehr selbstverständlich bereit sind. ","fid":"p__17"}]},{"docId":"D_000158-001-000","docUri":"D_000158-001-000.html","score":1,"contexts":[{"form":"gegebenenfalls","weight":"1","pos":93,"context":"...als Störer der künstlerischen Arbeit bezeichneten, den man <mark>gegebenenfalls<\/mark> ent sprechend behandeln werde. Der genaue Wortlaut der Aeusserungen...","fid":"p__29"}]},{"docId":"D_000130-012-000","docUri":"D_000130-012-000.html","score":1,"contexts":[{"form":"gegebenenfalls","weight":"1","pos":72,"context":" 1) Das Urteil <mark>gegebenenfalls<\/mark> gegen Sicherheitsleistung (§§ 710, 713 Abs....","fid":"p__18"}]},{"docId":"D_000013-008-000","docUri":"D_000013-008-000.html","score":1,"contexts":[{"form":"gegebenenfalls","weight":"1","pos":705,"context":"...Herausgebers oder eines Chefredakteurs erscheinen, an welche Verfügung <mark>gegebenenfalls<\/mark> der Bilderredakteur gebunden ist. Ich weiss aber von einer...","fid":"p__93"}]},{"docId":"D_000023-024-000","docUri":"D_000023-024-000.html","score":1,"contexts":[{"form":"gegebenenfalls","weight":"1","pos":97,"context":"...dieses Beschl. bekanntgegeben, ob je mand, <mark>gegebenenfalls<\/mark> wer, auf unlauteren Wege versuch te dg. den Emmerich...","fid":"p__22"}]},{"docId":"D_000193-180-000","docUri":"D_000193-180-000.html","score":1,"contexts":[{"form":"gegebenenfalls","weight":"1","pos":60,"context":"...erteilt. Auch habe ich ihn ermäch tigt, <mark>gegebenenfalls<\/mark> einen bedingten Vergleich abzuschliessen, konnte jedoch den Wortlaut...","fid":"p__16"}]},{"docId":"D_000072-015-000","docUri":"D_000072-015-000.html","score":1,"contexts":[{"form":"gegebenenfalls","weight":"1","pos":101,"context":"...Linderung wirtschaftlicher Not einer in Österreich ansässigen wie einer <mark>gegebenenfalls<\/mark> zuwandernden Judenschaft zu treuen Handen zu bewahren.","fid":"p__24"}]},{"docId":"D_000193-097-000","docUri":"D_000193-097-000.html","score":1,"contexts":[{"form":"gegebenenfalls","weight":"1","pos":246,"context":"...dass Herr K. von vornherein damit einverstanden ist, dass <mark>gegebenenfalls<\/mark> eine vom Gerichte abgeänderte Berichtigung zur Veröffentlichung gelangt....","fid":"p__22"}]}]}