{"stem":"gerechten","instances":[{"docId":"D_000042-003-000","docUri":"D_000042-003-000.html","score":1,"contexts":[{"form":"gerechten","weight":"1","pos":70,"context":"...jeden zweiten Tag telefonisch angerufen. Ich stehe dieser <mark>gerechten<\/mark> Sache immer gerne zu Verfügung.","fid":"p__11"}]},{"docId":"D_000193-060-000","docUri":"D_000193-060-000.html","score":1,"contexts":[{"form":"Gerechten","weight":"1","pos":50,"context":"...Unbestechlichen, die Richter ihrer Zeit und die allzeit <mark>Gerechten<\/mark> seien der Reihe nach alle nach Damaskus gegangen....","fid":"p__79"}]},{"docId":"D_000069-001-000","docUri":"D_000069-001-000.html","score":1,"contexts":[{"form":"gerechten","weight":"1","pos":34,"context":"...Ehrenschänder“, „Parasit“, „Schmierian“, „<mark>gerechten<\/mark> Lumpen“, nennt. Es ergibt sich nun die...","fid":"p__37"}]}]}