{"stem":"inten","instances":[{"docId":"D_000158-004-000","docUri":"D_000158-004-000.html","score":1,"contexts":[{"form":"Inten","weight":"1","pos":41,"context":"...Direktor Curiel) aussichtsreicher als ein solches gegen die <mark>Inten<\/mark> danz. Ich möchte den Anspruch in erster Linie...","fid":"p__29"}]},{"docId":"D_000076-006-000","docUri":"D_000076-006-000.html","score":1,"contexts":[{"form":"Inten","weight":"1","pos":361,"context":"...Art, Shakespeare zu übersetzen, verfolge. Diese <mark>Inten<\/mark> tionen, nämlich über die philologische Wörtlichkeit hinaus trotz...","fid":"p__36"}]}]}