{"stem":"integrierend","instances":[{"docId":"D_000113-007-000","docUri":"D_000113-007-000.html","score":1,"contexts":[{"form":"integrierender","weight":"1","pos":550,"context":"...hingewiesen, dass das in einem Inserat angekündigte Schriftwerk <mark>integrierender<\/mark> Bestandteil des Inserats sei. ","fid":"p__45"}]},{"docId":"D_000122-001-000","docUri":"D_000122-001-000.html","score":1,"contexts":[{"form":"integrierende","weight":"1","pos":499,"context":"...…“. Es ist unwahr, dass als dieses eine <mark>integrierende<\/mark>, wertverändernde Wort „goste“ statt „zart“ erkannt...","fid":"p__50"}]},{"docId":"D_000122-002-000","docUri":"D_000122-002-000.html","score":1,"contexts":[{"form":"integrierende","weight":"1","pos":477,"context":"...…“. Es ist unwahr, dass als dieses eine <mark>integrierende<\/mark>, wert verändernde Wort „goste“ statt „zarte“...","fid":"p__48"}]},{"docId":"D_000144-035-000","docUri":"D_000144-035-000.html","score":1,"contexts":[{"form":"integrierender","weight":"1","pos":305,"context":"...und uns enthält alle näheren Umstände und wird als <mark>integrierender<\/mark> Bestand teil unserer Vereinbarungen angesehen. Hinzuzufügen ist nur,...","fid":"p__11"}]},{"docId":"D_000144-061-000","docUri":"D_000144-061-000.html","score":1,"contexts":[{"form":"integrierender","weight":"1","pos":47,"context":"...und uns enthält alle näheren Umstände und wird als <mark>integrierender<\/mark> Bestandteil unserer Vereinbarungen angesehen. Hinzuzufügen ist nur, dass...","fid":"p__12"}]}]}