{"stem":"mittelsmann","instances":[{"docId":"D_000158-018-000","docUri":"D_000158-018-000.html","score":1,"contexts":[{"form":"Mittelsmann","weight":"1","pos":301,"context":"...nur im Vortrags manuskript vor. Es wurde durch den <mark>Mittelsmann<\/mark> (Dr. Ludwig Münz) Herrn Dr. Camill Hoffmann,...","fid":"p__104"}]},{"docId":"D_000075-001-000","docUri":"D_000075-001-000.html","score":1,"contexts":[{"form":"Mittelsmann","weight":"1","pos":136,"context":"...und sich bei ihm (Grossmann) durch einen <mark>Mittelsmann<\/mark> (vermutlich Kuh?) nach der Wahrheit erkundigt und...","fid":"p__21"}]}]}