{"stem":"obschon","instances":[{"docId":"D_000068-062-000","docUri":"D_000068-062-000.html","score":3,"contexts":[{"form":"obschon","weight":"1","pos":6655,"context":"...im Krieg einen Brief moti vieren, wenn er, <mark>obschon<\/mark> mit einem verdünnten Sätzchen, zugibt, dass so...","fid":"note__72"},{"form":"obschon","weight":"1","pos":7442,"context":"...Beklagte darüber gewundert, dass Herr Kraus, „<mark>obschon<\/mark> er Schrift steller ist (und obgleich beleidigende Angriffe das...","fid":"note__50"},{"form":"obschon","weight":"1","pos":7991,"context":"...die meines Gegners lebt in konservativen Kreisen fort, <mark>obschon<\/mark> sie vielleicht nicht wissen mögen, dass er noch heute...","fid":"note__27"}]},{"docId":"D_000068-074-000","docUri":"D_000068-074-000.html","score":2,"contexts":[{"form":"obschon","weight":"1","pos":2754,"context":"...Schwerindustriellen in jenem Kuplet-Machwerk gemeint haben will, <mark>obschon<\/mark> er deutlich gesagt hat, das Kuplet „","fid":"note__8"},{"form":"Obschon","weight":"1","pos":2913,"context":"...den Angriff eines unbekannten Herrn Reifferscheidt gegen Kerr. <mark>Obschon<\/mark> ich doch, im öffentlichen Kampfe stehend, gleichfalls Feinde...","fid":"note__27"}]},{"docId":"D_000112-081-000","docUri":"D_000112-081-000.html","score":1,"contexts":[{"form":"Obschon","weight":"1","pos":347,"context":" „<mark>Obschon<\/mark> die erwähnte Mitteilung der zwei Herren kein ern ster...","fid":"p__31"}]},{"docId":"D_000072-007-000","docUri":"D_000072-007-000.html","score":1,"contexts":[{"form":"obschon","weight":"1","pos":34,"context":" Und <mark>obschon<\/mark> ich meinem Meister Neues nicht zu melden habe, überreiche...","fid":"p__13"}]},{"docId":"D_000072-008-000","docUri":"D_000072-008-000.html","score":1,"contexts":[{"form":"obschon","weight":"1","pos":1460,"context":"...ausge sprochenen Gewissheit, dass der Wiener Polizeipräsident, <mark>obschon<\/mark> er ein Idiot ist, für das an mir von...","fid":"p__44"}]},{"docId":"D_000076-005-000","docUri":"D_000076-005-000.html","score":1,"contexts":[{"form":"obschon","weight":"1","pos":36,"context":"...ge wesen, deren Berechtigung Sie freilich sogar, <mark>obschon<\/mark> nur zum Teil anerkennen. Wir müssen Ihnen aber...","fid":"p__72"}]},{"docId":"D_000112-010-000","docUri":"D_000112-010-000.html","score":1,"contexts":[{"form":"Obschon","weight":"1","pos":72,"context":"...haben, und zwar dadurch, daß er schrieb: „<mark>Obschon<\/mark> die erwähnte Mitteilung der zwei Herren kein ernster Anlaß...","fid":"p__24"}]},{"docId":"D_000068-044-000","docUri":"D_000068-044-000.html","score":1,"contexts":[{"form":"obschon","weight":"1","pos":144,"context":" Darauf hat Herr Kraus, <mark>obschon<\/mark> er Schriftsteller ist (und obgleich beleidigende Angriffe das sind,...","fid":"p__21"}]}]}