{"stem":"paket","instances":[{"docId":"D_000169-001-000","docUri":"D_000169-001-000.html","score":1,"contexts":[{"form":"Paketes","weight":"1","pos":22,"context":"...entspreche diesem Wunsche des Verstorbenen durch Ueber mittlung dieses <mark>Paketes<\/mark> und gestatte mir im Sinne des Verstorbenen zu bemerken...","fid":"p__9"}]},{"docId":"D_000063-003-000","docUri":"D_000063-003-000.html","score":1,"contexts":[{"form":"Paket","weight":"1","pos":130,"context":"...Angestellten des photographischen Ateliers befördert wurde und diese das <mark>Paket<\/mark> keinen Augenblick aus der Hand gegeben hat. ","fid":"p__33"}]},{"docId":"D_000063-002-000","docUri":"D_000063-002-000.html","score":1,"contexts":[{"form":"Paket","weight":"1","pos":25,"context":"...die mir auf Befragen versicherte, daß sie das <mark>Paket<\/mark> keinen Augenblick aus der Hand gegeben hat. ","fid":"p__19"}]},{"docId":"D_000196-085-000","docUri":"D_000196-085-000.html","score":1,"contexts":[{"form":"Paket","weight":"1","pos":10,"context":"...d.M., das ich noch gestern erhielt. Das <mark>Paket<\/mark> mit den Fackeln habe ich gerade bekommen. ","fid":"p__7"}]},{"docId":"D_000196-083-000","docUri":"D_000196-083-000.html","score":1,"contexts":[{"form":"Paket","weight":"1","pos":75,"context":" Heute habe ich Ihnen ein <mark>Paket<\/mark> mit den Beilagen gesendet: ","fid":"p__7"}]}]}