{"stem":"rührt","instances":[{"docId":"D_000193-158-000","docUri":"D_000193-158-000.html","score":1,"contexts":[{"form":"rührt","weight":"1","pos":53,"context":"...die Grundrechte der Advoka tur und der freien Verteidigung <mark>rührt<\/mark>, zu unterstützen. Er führt aus, dass er...","fid":"p__49"}]},{"docId":"D_000125-049-000","docUri":"D_000125-049-000.html","score":1,"contexts":[{"form":"rührt","weight":"1","pos":260,"context":"...habe; ferner die Erklärung, dass der Aufführungsvertrag unbe <mark>rührt<\/mark> bleibe und dass trotz Zahlung des Pönales die Aufführung...","fid":"p__144"}]},{"docId":"D_000193-160-000","docUri":"D_000193-160-000.html","score":1,"contexts":[{"form":"rührt","weight":"1","pos":703,"context":"...an die Grundrechte der Advokatur und der freien Verteidigung <mark>rührt<\/mark>. ","fid":"p__33"}]},{"docId":"D_000027-003-000","docUri":"D_000027-003-000.html","score":1,"contexts":[{"form":"rührt","weight":"1","pos":344,"context":"..., die Mitteilung der Zeugin Kaus an den Privatanklägervertreter <mark>rührt<\/mark> von 2 Jahren her. – ","fid":"p__33"}]}]}