{"stem":"tempel","instances":[{"docId":"D_000002-009-000","docUri":"D_000002-009-000.html","score":2,"contexts":[{"form":"Tempel","weight":"1","pos":270,"context":"...etwa den Umstand, dass der Kl채ger im israelitischen <mark>Tempel<\/mark> gesehen worden ist, zur Erh채rtung der von ihr aufgestellten...","fid":"p__93"},{"form":"Tempel","weight":"1","pos":286,"context":"...der Wahrheit dient, festzustellen, dass er im <mark>Tempel<\/mark> nur erschienen ist, um einer Trauung beizuwohnen? Es...","fid":"p__93"}]},{"docId":"D_000002-012-000","docUri":"D_000002-012-000.html","score":1,"contexts":[{"form":"Tempels","weight":"1","pos":104,"context":"...gegenst채ndlichen Berichtigung noch das Beispiel mit dem Besuch des <mark>Tempels<\/mark> an und wies nach, dass es sich bei den...","fid":"p__32"}]},{"docId":"D_000072-012-002","docUri":"D_000072-012-002.html","score":1,"contexts":[{"form":"Tempels","weight":"1","pos":467,"context":"...ewigen Attribute Gottes. Sie sind die Bausteine des <mark>Tempels<\/mark>, aus dem es zu treiben gilt die H채ndler...","fid":"p__30"}]}]}