{"stem":"versöhnt","instances":[{"docId":"D_000112-016-000","docUri":"D_000112-016-000.html","score":1,"contexts":[{"form":"versöhnt","weight":"1","pos":177,"context":"...aber dadurch bewiesen, daß der Kerr publizistisch bereits <mark>versöhnt<\/mark> war und daß nur noch die Besiegelung durch persönlichen...","fid":"p__89"}]},{"docId":"D_000112-041-000","docUri":"D_000112-041-000.html","score":1,"contexts":[{"form":"versöhnt","weight":"1","pos":524,"context":"...hat, nachher aber durch Bürgermeister Reicke mit Reinhardt wieder <mark>versöhnt<\/mark> und zu sammengebracht worden ist. Dr. Kerr hat in...","fid":"p__68"}]},{"docId":"D_000112-018-000","docUri":"D_000112-018-000.html","score":1,"contexts":[{"form":"versöhnt","weight":"1","pos":230,"context":"...wird dadurch aber bewiesen, daß dieser publizistisch bereits <mark>versöhnt<\/mark> war und daß nur noch die Besiegelung durch persönlichen...","fid":"p__22"}]},{"docId":"D_000193-099-000","docUri":"D_000193-099-000.html","score":1,"contexts":[{"form":"versöhnt","weight":"1","pos":626,"context":"...von der Moral der richter lichen Begründung und so <mark>versöhnt<\/mark> auseinandergehen (und vielleicht auch streitende Nachbarsleute). Man müsste...","fid":"p__153"}]}]}