{"stem":"vorhan","instances":[{"docId":"D_000196-084-000","docUri":"D_000196-084-000.html","score":1,"contexts":[{"form":"vorhan","weight":"1","pos":275,"context":"...ihnen vorgegebene Interesse schon zur Zeit der inkriminierten Aeusserung <mark>vorhan<\/mark> den war. Dieser Strafausschliessungsgrund ist nur dann gegeben,...","fid":"p__64"}]},{"docId":"D_000193-043-000","docUri":"D_000193-043-000.html","score":1,"contexts":[{"form":"vorhan","weight":"1","pos":306,"context":"...bei jenen eine bei den Prager-Richtern immerhin <mark>vorhan<\/mark> dene Eigenschaft, nämlich die Unvoreingenommenheit, nicht unbe...","fid":"p__30"}]}]}